{
  "snapshot_1756468934_e8265d53": {
    "snapshot_id": "snapshot_1756468934_e8265d53",
    "timestamp": 1756468934.395155,
    "size_bytes": 10800,
    "chains_included": [
      "A",
      "B",
      "D"
    ],
    "block_count": {
      "A": 1,
      "B": 1,
      "D": 0
    },
    "integrity_hash": "13174893d925045fa743a44129b6ed1b",
    "compression_ratio": 3.374537037037037,
    "creation_time_seconds": 0.019329071044921875,
    "description": "Automatic snapshot 2025-08-29 21:02:14",
    "tags": [
      "automatic"
    ],
    "verified": false
  },
  "snapshot_1756480267_bed835bf": {
    "snapshot_id": "snapshot_1756480267_bed835bf",
    "timestamp": 1756480267.126966,
    "size_bytes": 11944,
    "chains_included": [
      "A",
      "B",
      "D"
    ],
    "block_count": {
      "A": 1,
      "B": 1,
      "D": 0
    },
    "integrity_hash": "c3604e67369288daa9390cd70ab02240",
    "compression_ratio": 3.1338747488278633,
    "creation_time_seconds": 0.02493000030517578,
    "description": "Automatic snapshot 2025-08-30 00:11:07",
    "tags": [
      "automatic"
    ],
    "verified": false
  },
  "snapshot_1756483867_65377354": {
    "snapshot_id": "snapshot_1756483867_65377354",
    "timestamp": 1756483867.138043,
    "size_bytes": 11832,
    "chains_included": [
      "A",
      "B",
      "D"
    ],
    "block_count": {
      "A": 1,
      "B": 1,
      "D": 0
    },
    "integrity_hash": "4abde57fba823799d818c45af25b58b2",
    "compression_ratio": 3.163370520622042,
    "creation_time_seconds": 0.02297210693359375,
    "description": "Automatic snapshot 2025-08-30 01:11:07",
    "tags": [
      "automatic"
    ],
    "verified": false
  },
  "snapshot_1756533233_bacd8599": {
    "snapshot_id": "snapshot_1756533233_bacd8599",
    "timestamp": 1756533233.142061,
    "size_bytes": 11832,
    "chains_included": [
      "A",
      "B",
      "D"
    ],
    "block_count": {
      "A": 1,
      "B": 1,
      "D": 0
    },
    "integrity_hash": "4abde57fba823799d818c45af25b58b2",
    "compression_ratio": 3.163370520622042,
    "creation_time_seconds": 0.02228999137878418,
    "description": "Automatic snapshot 2025-08-30 14:53:53",
    "tags": [
      "automatic"
    ],
    "verified": false
  },
  "snapshot_1756540721_49cf0b41": {
    "snapshot_id": "snapshot_1756540721_49cf0b41",
    "timestamp": 1756540721.3560371,
    "size_bytes": 11832,
    "chains_included": [
      "A",
      "B",
      "D"
    ],
    "block_count": {
      "A": 1,
      "B": 1,
      "D": 0
    },
    "integrity_hash": "4abde57fba823799d818c45af25b58b2",
    "compression_ratio": 3.163370520622042,
    "creation_time_seconds": 0.023183822631835938,
    "description": "Automatic snapshot 2025-08-30 16:58:41",
    "tags": [
      "automatic"
    ],
    "verified": false
  },
  "snapshot_1756544841_8aaed9d1": {
    "snapshot_id": "snapshot_1756544841_8aaed9d1",
    "timestamp": 1756544841.4735801,
    "size_bytes": 11832,
    "chains_included": [
      "A",
      "B",
      "D"
    ],
    "block_count": {
      "A": 1,
      "B": 1,
      "D": 0
    },
    "integrity_hash": "4abde57fba823799d818c45af25b58b2",
    "compression_ratio": 3.163370520622042,
    "creation_time_seconds": 0.02603292465209961,
    "description": "Automatic snapshot 2025-08-30 18:07:21",
    "tags": [
      "automatic"
    ],
    "verified": false
  }
}